setup.cfg
setup.py
rethinkdb/__init__.py
rethinkdb/_backup.py
rethinkdb/_dump.py
rethinkdb/_export.py
rethinkdb/_import.py
rethinkdb/_index_rebuild.py
rethinkdb/_negative_zero_check.py
rethinkdb/_restore.py
rethinkdb/ast.py
rethinkdb/docs.py
rethinkdb/errors.py
rethinkdb/net.py
rethinkdb/ql2_pb2.py
rethinkdb/query.py
rethinkdb/version.py
rethinkdb/asyncio_net/__init__.py
rethinkdb/asyncio_net/net_asyncio.py
rethinkdb/backports/ssl_match_hostname/LICENSE.txt
rethinkdb/backports/ssl_match_hostname/README.txt
rethinkdb/backports/ssl_match_hostname/__init__.py
rethinkdb/gevent_net/__init__.py
rethinkdb/gevent_net/net_gevent.py
rethinkdb/tornado_net/__init__.py
rethinkdb/tornado_net/net_tornado.py
rethinkdb/twisted_net/__init__.py
rethinkdb/twisted_net/net_twisted.py
rethinkdb_next.egg-info/PKG-INFO
rethinkdb_next.egg-info/SOURCES.txt
rethinkdb_next.egg-info/dependency_links.txt
rethinkdb_next.egg-info/entry_points.txt
rethinkdb_next.egg-info/top_level.txt
rethinkdb_next.egg-info/zip-safe