Metadata-Version: 1.0
Name: rethinkdb-next
Version: 2.2.0.post1
Summary: Python driver library for the RethinkDB database server from next branch
Home-page: http://rethinkdb.com
Author: UNKNOWN
Author-email: UNKNOWN
License: UNKNOWN
Platform: UNKNOWN
